gopro_sdk/__init__.py
gopro_sdk/ble_uuid.py
gopro_sdk/client.py
gopro_sdk/config.py
gopro_sdk/exceptions.py
gopro_sdk/logging_config.py
gopro_sdk/multi_camera.py
gopro_sdk/rich_utils.py
gopro_sdk/state_parser.py
gopro_sdk/commands/__init__.py
gopro_sdk/commands/base.py
gopro_sdk/commands/ble_commands.py
gopro_sdk/commands/http_commands.py
gopro_sdk/commands/media_commands.py
gopro_sdk/commands/webcam_commands.py
gopro_sdk/connection/__init__.py
gopro_sdk/connection/ble_manager.py
gopro_sdk/connection/ble_scanner.py
gopro_sdk/connection/health_check.py
gopro_sdk/connection/http_manager.py
gopro_sdk/proto/__init__.py
gopro_sdk/proto/camera_control_pb2.py
gopro_sdk/proto/cohn_pb2.py
gopro_sdk/proto/live_streaming_pb2.py
gopro_sdk/proto/media_pb2.py
gopro_sdk/proto/network_management_pb2.py
gopro_sdk/proto/preset_status_pb2.py
gopro_sdk/proto/request_get_preset_status_pb2.py
gopro_sdk/proto/response_generic_pb2.py
gopro_sdk/proto/set_camera_control_status_pb2.py
gopro_sdk/proto/turbo_transfer_pb2.py
gopro_sdk_py-1.0.4.dist-info/METADATA
gopro_sdk_py-1.0.4.dist-info/WHEEL
gopro_sdk_py-1.0.4.dist-info/licenses/LICENSE
gopro_sdk_py-1.0.4.dist-info/RECORD
