Metadata-Version: 2.4
Name: gopro-sdk-py
Version: 1.0.4
Summary: A Python SDK for controlling GoPro cameras, optimized for multi-camera COHN scenarios
Project-URL: Homepage, https://github.com/sean2077/gopro-sdk-py
Project-URL: Repository, https://github.com/sean2077/gopro-sdk-py.git
Project-URL: Issues, https://github.com/sean2077/gopro-sdk-py/issues
Project-URL: Changelog, https://github.com/sean2077/gopro-sdk-py/blob/main/CHANGELOG.md
Project-URL: Documentation, https://sean2077.github.io/gopro-sdk-py/
Author-email: sean2077 <sean2077@users.noreply.github.com>
Maintainer-email: sean2077 <sean2077@users.noreply.github.com>
License-Expression: MIT
License-File: LICENSE
Keywords: ble,bluetooth,camera,cohn,gopro,multi-camera,sdk
Classifier: Development Status :: 4 - Beta
Classifier: Intended Audience :: Developers
Classifier: Operating System :: OS Independent
Classifier: Programming Language :: Python :: 3
Classifier: Programming Language :: Python :: 3.12
Classifier: Programming Language :: Python :: 3.13
Classifier: Topic :: Multimedia :: Video
Classifier: Topic :: Software Development :: Libraries :: Python Modules
Classifier: Typing :: Typed
Requires-Python: >=3.12
Requires-Dist: aiohttp>=3.13
Requires-Dist: bleak>=0.22
Requires-Dist: construct>=2.10
Requires-Dist: open-gopro>=0.22
Requires-Dist: rich>=14.0
Requires-Dist: tinydb>=4.8
